tree_sitter_autolang/__init__.py
tree_sitter_autolang/__init__.pyi
tree_sitter_autolang/_binding.abi3.so
tree_sitter_autolang/binding.c
tree_sitter_autolang/py.typed
tree_sitter_autolang-0.4.1.dist-info/METADATA
tree_sitter_autolang-0.4.1.dist-info/WHEEL
tree_sitter_autolang-0.4.1.dist-info/top_level.txt
tree_sitter_autolang-0.4.1.dist-info/RECORD
tree_sitter_autolang-0.4.1.dist-info/licenses/LICENSE
