Metadata-Version: 2.4
Name: tree-sitter-autolang
Version: 0.4.1
Summary: AutoLang Parser
Author-email: AutoLang-Dev <contact@autolang.dev>
License: MIT
Project-URL: Homepage, https://github.com/autolang-dev/tree-sitter-autolang
Keywords: incremental,parsing,tree-sitter,autolang
Classifier: Intended Audience :: Developers
Classifier: Topic :: Software Development :: Compilers
Classifier: Topic :: Text Processing :: Linguistic
Classifier: Typing :: Typed
Requires-Python: >=3.10
License-File: LICENSE
Provides-Extra: core
Requires-Dist: tree-sitter~=0.24; extra == "core"
Dynamic: license-file
